marketdata/__init__.py
marketdata/api_error.py
marketdata/api_status.py
marketdata/client.py
marketdata/docs.py
marketdata/exceptions.py
marketdata/internal_settings.py
marketdata/logger.py
marketdata/params.py
marketdata/retry.py
marketdata/sdk_error.py
marketdata/settings.py
marketdata/types.py
marketdata/utils.py
marketdata/input_types/__init__.py
marketdata/input_types/base.py
marketdata/input_types/funds.py
marketdata/input_types/markets.py
marketdata/input_types/options.py
marketdata/input_types/stocks.py
marketdata/output_handlers/__init__.py
marketdata/output_handlers/base.py
marketdata/output_handlers/pandas.py
marketdata/output_handlers/polars.py
marketdata/output_types/__init__.py
marketdata/output_types/funds_candles.py
marketdata/output_types/markets_status.py
marketdata/output_types/options_chain.py
marketdata/output_types/options_expirations.py
marketdata/output_types/options_lookup.py
marketdata/output_types/options_quotes.py
marketdata/output_types/options_strikes.py
marketdata/output_types/stocks_candles.py
marketdata/output_types/stocks_earnings.py
marketdata/output_types/stocks_news.py
marketdata/output_types/stocks_prices.py
marketdata/output_types/stocks_quotes.py
marketdata/resources/__init__.py
marketdata/resources/base.py
marketdata/resources/funds/__init__.py
marketdata/resources/funds/candles.py
marketdata/resources/markets/__init__.py
marketdata/resources/markets/status.py
marketdata/resources/options/__init__.py
marketdata/resources/options/chain.py
marketdata/resources/options/expirations.py
marketdata/resources/options/lookup.py
marketdata/resources/options/quotes.py
marketdata/resources/options/strikes.py
marketdata/resources/stocks/__init__.py
marketdata/resources/stocks/candles.py
marketdata/resources/stocks/earnings.py
marketdata/resources/stocks/news.py
marketdata/resources/stocks/prices.py
marketdata/resources/stocks/quotes.py
marketdata_sdk_py-1.1.0.dist-info/METADATA
marketdata_sdk_py-1.1.0.dist-info/WHEEL
marketdata_sdk_py-1.1.0.dist-info/licenses/LICENSE
marketdata_sdk_py-1.1.0.dist-info/RECORD
