Metadata-Version: 2.4
Name: marketdata-sdk-py
Version: 1.1.0
Summary: Official Python SDK for the Market Data API - Real-time stock prices, options data, market status, and more
Project-URL: Homepage, https://www.marketdata.app
Project-URL: Repository, https://github.com/MarketDataApp/sdk-py
Project-URL: Documentation, https://www.marketdata.app/docs/sdk/py
Project-URL: Issues, https://github.com/MarketDataApp/sdk-py/issues
Author-email: Market Data <support@marketdata.app>
License: MIT
License-File: LICENSE
Keywords: api,candles,dataframe,earnings,finance,financial-data,financial-news,market-data,market-status,marketdata,marketdata-app,mutual-funds,ohlcv,options,options-chain,options-trading,pandas,polars,quotes,real-time-data,sdk,stock-market,stock-prices,stocks,trading,trading-data
Classifier: Development Status :: 5 - Production/Stable
Classifier: Intended Audience :: Developers
Classifier: Intended Audience :: Financial and Insurance Industry
Classifier: License :: OSI Approved :: MIT License
Classifier: Operating System :: OS Independent
Classifier: Programming Language :: Python
Classifier: Programming Language :: Python :: 3
Classifier: Programming Language :: Python :: 3.10
Classifier: Programming Language :: Python :: 3.11
Classifier: Programming Language :: Python :: 3.12
Classifier: Topic :: Internet :: WWW/HTTP :: Dynamic Content
Classifier: Topic :: Office/Business :: Financial
Classifier: Topic :: Office/Business :: Financial :: Investment
Classifier: Topic :: Software Development :: Libraries :: Python Modules
Requires-Python: >=3.10
Requires-Dist: httpx>=0.28.1
Requires-Dist: pydantic-settings>=2.12.0
Requires-Dist: pydantic>=2.12.5
Requires-Dist: pytz>=2024.1
Requires-Dist: tenacity>=9.1.2
Provides-Extra: pandas
Requires-Dist: pandas>=2.3.3; extra == 'pandas'
Provides-Extra: polars
Requires-Dist: polars-lts-cpu>=1.33.1; extra == 'polars'
